harmony_connect_client/__init__.py
harmony_connect_client/api_client.py
harmony_connect_client/configuration.py
harmony_connect_client/rest.py
harmony_connect_client/api/__init__.py
harmony_connect_client/api/chains_api.py
harmony_connect_client/api/entries_api.py
harmony_connect_client/api/info_api.py
harmony_connect_client/models/__init__.py
harmony_connect_client/models/all_info.py
harmony_connect_client/models/all_info_links.py
harmony_connect_client/models/chain.py
harmony_connect_client/models/chain_create.py
harmony_connect_client/models/chain_data.py
harmony_connect_client/models/chain_data_dblock.py
harmony_connect_client/models/chain_data_eblock.py
harmony_connect_client/models/chain_data_entries.py
harmony_connect_client/models/chain_link.py
harmony_connect_client/models/chain_list.py
harmony_connect_client/models/chain_list_data.py
harmony_connect_client/models/chain_short.py
harmony_connect_client/models/entry.py
harmony_connect_client/models/entry_create.py
harmony_connect_client/models/entry_data.py
harmony_connect_client/models/entry_data_dblock.py
harmony_connect_client/models/entry_data_eblock.py
harmony_connect_client/models/entry_list.py
harmony_connect_client/models/entry_list_chain.py
harmony_connect_client/models/entry_list_data.py
harmony_connect_client/models/entry_search_response.py
harmony_connect_client/models/entry_search_response_data.py
harmony_connect_client/models/entry_short.py
harmony_connect_client/models/search_body.py
test/__init__.py
test/test_all_info.py
test/test_all_info_links.py
test/test_chain.py
test/test_chain_create.py
test/test_chain_data.py
test/test_chain_data_dblock.py
test/test_chain_data_eblock.py
test/test_chain_data_entries.py
test/test_chain_link.py
test/test_chain_list.py
test/test_chain_list_data.py
test/test_chain_short.py
test/test_chains_api.py
test/test_entries_api.py
test/test_entry.py
test/test_entry_create.py
test/test_entry_data.py
test/test_entry_data_dblock.py
test/test_entry_data_eblock.py
harmony_connect_client-1.0.7.dist-info/LICENSE
harmony_connect_client-1.0.7.dist-info/METADATA
harmony_connect_client-1.0.7.dist-info/WHEEL
harmony_connect_client-1.0.7.dist-info/top_level.txt
harmony_connect_client-1.0.7.dist-info/RECORD
