Metadata-Version: 2.1
Name: harmony-connect-client
Version: 1.0.7
Summary: Harmony Connect
Home-page: https://github.com/FactomProject/factom-harmony-connect-python-client
Author: UNKNOWN
Author-email: harmony-support@factom.com
License: UNKNOWN
Keywords: factom,factom-blockchain,blockchain,blockchain-as-a-service,client-library,Harmony Connect
Platform: UNKNOWN
Requires-Dist: urllib3 (>=1.15)
Requires-Dist: six (>=1.10)
Requires-Dist: certifi
Requires-Dist: python-dateutil
